python_jose_TPM/__init__.py
python_jose_TPM/constants.py
python_jose_TPM/exceptions.py
python_jose_TPM/jwe.py
python_jose_TPM/jwk.py
python_jose_TPM/jws.py
python_jose_TPM/jwt.py
python_jose_TPM/utils.py
python_jose_TPM/backends/__init__.py
python_jose_TPM/backends/_asn1.py
python_jose_TPM/backends/base.py
python_jose_TPM/backends/cryptography_backend.py
python_jose_TPM/backends/ecdsa_backend.py
python_jose_TPM/backends/native.py
python_jose_TPM/backends/rsa_backend.py
python_jose_TPM-0.1.1.dist-info/LICENSE
python_jose_TPM-0.1.1.dist-info/METADATA
python_jose_TPM-0.1.1.dist-info/WHEEL
python_jose_TPM-0.1.1.dist-info/top_level.txt
python_jose_TPM-0.1.1.dist-info/RECORD
