Metadata-Version: 2.1
Name: python-jose-TPM
Version: 0.1.1
Summary: TPM based python JOSE implementation
Author: Henry Gadacz
License: MIT License
Keywords: TPM,TSS,JSON,JOSE,JWE,JWS,JWT,pytss
Classifier: License :: OSI Approved :: MIT License
Classifier: Programming Language :: Python
Classifier: Programming Language :: Python :: 3 :: Only
Classifier: Programming Language :: Python :: 3.10
Requires-Python: >=3.10
License-File: LICENSE
Requires-Dist: tpm2-pytss (==1.2.0)
Requires-Dist: ecdsa (==0.18.0)
Requires-Dist: pyasn1 (==0.4.8)
Requires-Dist: rsa (==4.9)
